image_uploader/__init__.py
image_uploader_sdk-0.1.0.dist-info/METADATA
image_uploader_sdk-0.1.0.dist-info/WHEEL
image_uploader_sdk-0.1.0.dist-info/top_level.txt
image_uploader_sdk-0.1.0.dist-info/RECORD
